[{"name":"Chiến khu Tân Trào","allDocument":"Mục Lục [Thu / Mở] Vị trí địa lý Các địa danh nằm trong chiến khu Tham khảo Chiến khu Tân Trào Cây đa Tân Trào Thành lập 1945 Vị trí Thôn Tân Lập, xã Tân Trào, huyện Sơn Dương, tỉnh Tuyên Quang Giám đốc Hoàng Như Loan Trang web Du lịch Tân Trào Lán Nà Lừa Chiến khu Tân Trào là khu di tích lịch sử của cách mạng Việt Nam thời kỳ Cách mạng tháng Tám. Hiện nay, nơi đây đã được thủ tướng chính phủ Việt Nam đưa vào danh sách xếp hạng 23 di tích quốc gia đặc biệt. Tân Trào là thủ đô lâm thời của khu giải phóng, nơi Ðảng Cộng sản Việt Nam tiến hành hội nghị toàn quốc ngày 13 tháng 8 năm 1945 để quyết định tổng khởi nghĩa. Ðại hội quốc dân đã họp tại đây ngày 16 tháng 8 năm 1945, thông qua 10 chính sách lớn của Việt Minh, bầu ra một chính phủ lâm thời do Hồ Chí Minh làm chủ tịch và quân giải phóng Việt Nam làm lễ ra quân. Tân Trào là tên mới, được hợp nhất từ hai xã Tân Lập và Hồng Thái vào năm 1945 (trước đây còn gọi là Kim Long và Kim Châu). Vị trí địa lý","properties":{"Cây đa Tân Trào":"Cây đa Tân Trào","Thành lập":"1945","Vị trí":"Thôn Tân Lập, xã Tân Trào, huyện Sơn Dương, tỉnh Tuyên Quang","Giám đốc":"Hoàng Như Loan","Trang web":"Du lịch Tân Trào"},"description":"Chiến khu Tân Trào là khu di tích lịch sử của cách mạng Việt Nam thời kỳ Cách mạng tháng Tám. Hiện nay, nơi đây đã được thủ tướng chính phủ Việt Nam đưa vào danh sách xếp hạng 23 di tích quốc gia đặc biệt. Tân Trào là thủ đô lâm thời của khu giải phóng, nơi Ðảng Cộng sản Việt Nam tiến hành hội nghị toàn quốc ngày 13 tháng 8 năm 1945 để quyết định tổng khởi nghĩa. Ðại hội quốc dân đã họp tại đây ngày 16 tháng 8 năm 1945, thông qua 10 chính sách lớn của Việt Minh, bầu ra một chính phủ lâm thời do Hồ Chí Minh làm chủ tịch và quân giải phóng Việt Nam làm lễ ra quân.\nTân Trào là tên mới, được hợp nhất từ hai xã Tân Lập và Hồng Thái vào năm 1945 (trước đây còn gọi là Kim Long và Kim Châu).\n\n\n","image":"image/3acb617b-c53a-4a6a-a30a-78a916ce81d0.png","source":"https://nguoikesu.com/dia-danh/chien-khu-tan-trao"},{"name":"chùa Phổ Minh","allDocument":"Mục Lục [Thu / Mở] Lịch sử Kiến trúc Tháp Phổ Minh Tham khảo Chùa Phổ Minh 普明寺 (Phổ Minh tự) Tháp chùa Phổ Minh Vị trí Quốc gia Việt Nam Địa chỉ thôn Tức Mạc, thành phố Nam Định Thông tin Khởi lập 1061 Chủ đề:Phật giáo Chùa Phổ Minh (Phổ Minh tự 普明寺) hay chùa Tháp là một ngôi chùa ở thôn Tức Mạc, nằm cách thành phố Nam Định khoảng 5 km về phía bắc. Năm 2012, di tích lịch sử và kiến trúc nghệ thuật đền Trần và chùa Phổ Minh được xếp hạng di tích quốc gia đặc biệt. Lịch sử","properties":{"Chùa Phổ Minh 普明寺 (Phổ Minh tự)":"","Tháp chùa Phổ Minh":"Tháp chùa Phổ Minh","Vị trí":"","Quốc gia":"Việt Nam","Địa chỉ":"thôn Tức Mạc, thành phố Nam Định","Thông tin":"","Khởi lập":"1061","Chủ đề:Phật giáo":"Chủ đề:Phật giáo"},"description":"Chùa Phổ Minh (Phổ Minh tự 普明寺) hay chùa Tháp là một ngôi chùa ở thôn Tức Mạc, nằm cách thành phố Nam Định khoảng 5 km về phía bắc. Năm 2012, di tích lịch sử và kiến trúc nghệ thuật đền Trần và chùa Phổ Minh được xếp hạng di tích quốc gia đặc biệt.\n\n\n","image":"image/0ae03430-2c94-423b-958e-2cda942f8a2a.png","source":"https://nguoikesu.com/dia-danh/chua-pho-minh"},{"name":"chùa Thầy","allDocument":"Mục Lục [Thu / Mở] Lịch sử Truyền thuyết Hóa thân chuyển thế Kiến trúc Điêu khắc trong chùa Hệ thống chùa trên núi Di sản văn hóa Lễ hội và văn hóa Các đời trụ trì Chùa Thầy Vị trí Quốc gia Việt Nam Địa chỉ Sài Sơn, huyện Quốc Oai, Hà Nội Thông tin Tông phái Thiền Ti-ni-đa-lưu-chi Khởi lập Chùa được xây dựng từ thời nhà Lý Thầy Thiền sư Từ Đạo Hạnh Quản lý Giáo hội Phật giáo Việt Nam Chủ đề:Phật giáo Chùa Thầy là một ngôi chùa ở chân núi Sài Sơn, huyện Quốc Oai, tỉnh Hà Tây cũ, nay là xã Sài Sơn, huyện Quốc Oai, Hà Nội, cách trung tâm Hà Nội khoảng 20 km về phía Tây nam, đi theo đường cao tốc Láng - Hòa Lạc. Sài Sơn có tên Nôm là núi Thầy, nên chùa được gọi là chùa Thầy. Chùa được xây dựng từ thời nhà Đinh. Đây từng là nơi tu hành của Thiền sư Từ Đạo Hạnh, lúc này núi Thầy còn gọi là núi Phật Tích. Lịch sử","properties":{"Chùa Thầy":"","Vị trí":"","Quốc gia":"Việt Nam","Địa chỉ":"Sài Sơn, huyện Quốc Oai, Hà Nội","Thông tin":"","Tông phái":"Thiền Ti-ni-đa-lưu-chi","Khởi lập":"Chùa được xây dựng từ thời nhà Lý","Thầy":"Thiền sư Từ Đạo Hạnh","Quản lý":"Giáo hội Phật giáo Việt Nam","Chủ đề:Phật giáo":"Chủ đề:Phật giáo"},"description":"Chùa Thầy là một ngôi chùa ở chân núi Sài Sơn, huyện Quốc Oai, tỉnh Hà Tây cũ, nay là xã Sài Sơn, huyện Quốc Oai, Hà Nội, cách trung tâm Hà Nội khoảng 20 km về phía Tây nam, đi theo đường cao tốc Láng - Hòa Lạc. Sài Sơn có tên Nôm là núi Thầy, nên chùa được gọi là chùa Thầy. Chùa được xây dựng từ thời nhà Đinh. Đây từng là nơi tu hành của Thiền sư Từ Đạo Hạnh, lúc này núi Thầy còn gọi là núi Phật Tích.\n\n\n","image":null,"source":"https://nguoikesu.com/dia-danh/chua-thay"},{"name":"Cố đô Hoa Lư","properties":{},"description":"Cố đô Hoa Lư là quần thể di tích quốc gia đặc biệt quan trọng của Việt Nam đồng thời là một trong 4 vùng lõi của quần thể di sản thế giới Tràng An đã được UNESCO công nhận. Hệ thống di tích ở Hoa Lư liên quan đến sự nghiệp của các nhân vật lịch sử thuộc ba triều đại nhà Đinh, nhà Tiền Lê và khởi đầu nhà Lý, tính từ Đinh Tiên Hoàng đến Lý Thái Tông trong lịch sử. Hoa Lư là kinh đô đầu tiên của nhà nước phong kiến Trung ương tập quyền ở Việt Nam với các dấu ấn lịch sử: thống nhất giang sơn, đánh Tống - dẹp Chiêm và phát tích quá trình định đô Hà Nội. Năm 1010 vua Lý Thái Tổ dời kinh đô từ Hoa Lư (Ninh Bình) về Thăng Long (Hà Nội), Hoa Lư trở thành Cố đô. Các triều vua Lý, Trần, Lê, Nguyễn sau đó dù không đóng đô ở Hoa Lư nữa nhưng vẫn cho tu bổ và xây dựng thêm ở đây nhiều công trình kiến trúc như đền, lăng, đình, chùa, phủ… Khu di tích lịch sử Cố đô Hoa Lư hiện nay có diện tích quy hoạch 13,87 km² thuộc tỉnh Ninh Bình. Với bề dày thời gian hơn 1000 năm, Cố đô Hoa Lư là nơi lưu trữ các di tích lịch sử qua nhiều thời đại.\n\n\n","image":"image/1e213388-72f3-4952-b2e1-c7949f046fce.png","allDocument":"Mục Lục [Thu / Mở] Tổng quan Lịch sử Kinh đô Hoa Lư Khu di tích Cố đô Hoa Lư Các nhóm di tích Kiến trúc đền thờ Kiến trúc đình làng Kiến trúc chùa cổ Hệ thống lăng, bia Hệ thống phủ, miếu Dấu tích kinh thành Cung điện dưới lòng đất Thành thiên tạo Đô thị cổ Hoa Lư Bảo tồn và phát huy Phục dựng, tu bổ di tích Di sản văn hóa thế giới Lễ hội cố đô Hoa Lư Hành trình thăm viếng của du khách Tham khảo Chú thích Thư mục Cố đô Hoa Lư là quần thể di tích quốc gia đặc biệt quan trọng của Việt Nam đồng thời là một trong 4 vùng lõi của quần thể di sản thế giới Tràng An đã được UNESCO công nhận. Hệ thống di tích ở Hoa Lư liên quan đến sự nghiệp của các nhân vật lịch sử thuộc ba triều đại nhà Đinh, nhà Tiền Lê và khởi đầu nhà Lý, tính từ Đinh Tiên Hoàng đến Lý Thái Tông trong lịch sử. Hoa Lư là kinh đô đầu tiên của nhà nước phong kiến Trung ương tập quyền ở Việt Nam với các dấu ấn lịch sử: thống nhất giang sơn, đánh Tống - dẹp Chiêm và phát tích quá trình định đô Hà Nội. Năm 1010 vua Lý Thái Tổ dời kinh đô từ Hoa Lư (Ninh Bình) về Thăng Long (Hà Nội), Hoa Lư trở thành Cố đô. Các triều vua Lý, Trần, Lê, Nguyễn sau đó dù không đóng đô ở Hoa Lư nữa nhưng vẫn cho tu bổ và xây dựng thêm ở đây nhiều công trình kiến trúc như đền, lăng, đình, chùa, phủ… Khu di tích lịch sử Cố đô Hoa Lư hiện nay có diện tích quy hoạch 13,87 km² thuộc tỉnh Ninh Bình. Với bề dày thời gian hơn 1000 năm, Cố đô Hoa Lư là nơi lưu trữ các di tích lịch sử qua nhiều thời đại. Phong cảnh cố đô nhìn từ núi Mã Yên Cửa Đông vào Đền Đinh Lê Tổng quan","source":"https://nguoikesu.com/dia-danh/co-do-hoa-lu"},{"name":"Dinh Độc Lập","allDocument":"Mục Lục [Thu / Mở] Lịch sử Dinh Norodom thời Pháp thuộc Dinh Độc Lập thời Việt Nam Cộng hòa Sau năm 1975 Đặc điểm Một số hình ảnh Dinh Độc Lập Mặt tiền Dinh Độc Lập Thông tin chung Tên cũ Dinh Norodom Dạng Dinh Toàn quyền, Dinh Tổng thống Địa điểm 135 Nam Kỳ khởi nghĩa, phường Bến Nghé, quận 1, Thành phố Hồ Chí Minh, Việt Nam Tọa độ 10°46′40″B 106°41′46″Đ / 10,777749°B 106,696105°Đ Xây dựng Khởi công 1 tháng 7 năm 1962 Hoàn thành 31 tháng 10 năm 1966 Chiều cao 26m Diện tích sàn 120.000 Chiều cao 26m Thiết kế Kiến trúc sư Ngô Viết Thụ Kỹ sư công chính Phan Văn Điển Dinh Độc Lập (tên gọi trước đây là dinh Norodom, ngày nay còn gọi là dinh Thống Nhất hay hội trường Thống Nhất) là một công trình kiến trúc, tòa nhà ở Thành phố Hồ Chí Minh. Nó từng là nơi ở và làm việc của Tổng thống Việt Nam Cộng hòa. Hiện nay, nó đã được chính phủ Việt Nam xếp hạng là di tích quốc gia đặc biệt. Lịch sử","properties":{"Dinh Độc Lập":"","Mặt tiền Dinh Độc Lập":"Mặt tiền Dinh Độc Lập","Thông tin chung":"","Tên cũ":"Dinh Norodom","Dạng":"Dinh Toàn quyền, Dinh Tổng thống","Địa điểm":"135 Nam Kỳ khởi nghĩa, phường Bến Nghé, quận 1, Thành phố Hồ Chí Minh, Việt Nam","Tọa độ":"10°46′40″B 106°41′46″Đ / 10,777749°B 106,696105°Đ","Xây dựng":"","Khởi công":"1 tháng 7 năm 1962","Hoàn thành":"31 tháng 10 năm 1966","Chiều cao":"26m","Diện tích sàn":"120.000","Thiết kế":"","Kiến trúc sư":"Ngô Viết Thụ","Kỹ sư công chính":"Phan Văn Điển"},"description":"Dinh Độc Lập (tên gọi trước đây là dinh Norodom, ngày nay còn gọi là dinh Thống Nhất hay hội trường Thống Nhất) là một công trình kiến trúc, tòa nhà ở Thành phố Hồ Chí Minh. Nó từng là nơi ở và làm việc của Tổng thống Việt Nam Cộng hòa. Hiện nay, nó đã được chính phủ Việt Nam xếp hạng là di tích quốc gia đặc biệt.\n\n\n","image":"image/470b3236-4e76-42b3-bf32-43ec3ba336c3.png","source":"https://nguoikesu.com/dia-danh/dinh-doc-lap"},{"name":"Đền Hùng","properties":{},"description":"Đền Hùng là tên gọi khái quát của Khu di tích lịch sử Đền Hùng - quần thể đền chùa thờ phụng các Vua Hùng và tôn thất của nhà vua trên núi Nghĩa Lĩnh, gắn với Giỗ Tổ Hùng Vương - Lễ hội Đền Hùng được tổ chức tại địa điểm đó hàng năm vào ngày 10 tháng 3 âm lịch. Hiện nay, theo các tài liệu khoa học đã công bố đa số đều thống nhất nền móng kiến trúc đền Hùng bắt đầu được xây dựng từ thời vua Đinh Tiên Hoàng trị vì. Đến thời Hậu Lê (thế kỷ 15) được xây dựng hoàn chỉnh theo quy mô như hiện tại.\n\n\n","image":null,"allDocument":"Mục Lục [Thu / Mở] Vị trí Quá trình phát triển Đặc điểm Các di tích chính Hành trình của du khách Lễ hội đền Hùng Trống đồng tại Đền Hùng Chú thích Xem thêm Lăng Hùng vương trên đỉnh núi Nghĩa Lĩnh Đền Hùng là tên gọi khái quát của Khu di tích lịch sử Đền Hùng - quần thể đền chùa thờ phụng các Vua Hùng và tôn thất của nhà vua trên núi Nghĩa Lĩnh, gắn với Giỗ Tổ Hùng Vương - Lễ hội Đền Hùng được tổ chức tại địa điểm đó hàng năm vào ngày 10 tháng 3 âm lịch. Hiện nay, theo các tài liệu khoa học đã công bố đa số đều thống nhất nền móng kiến trúc đền Hùng bắt đầu được xây dựng từ thời vua Đinh Tiên Hoàng trị vì. Đến thời Hậu Lê (thế kỷ 15) được xây dựng hoàn chỉnh theo quy mô như hiện tại. Vị trí","source":"https://nguoikesu.com/dia-danh/den-hung"},{"name":"Đền Ngọc Sơn","allDocument":"Mục Lục [Thu / Mở] Lịch sử Công trình -Kiến trúc xung quanh Đền Ngọc Sơn Tháp Bút Đài Nghiên Cầu Thê Húc Đắc Nguyệt Lâu Đền thờ Trấn Ba Đình Ảnh Tham khảo Đền Ngọc Sơn di tích quốc gia đặc biệt Cổng đền Ngọc Sơn: trán cổng ghi ba chữ \"Đắc nguyệt lâu\" 得月樓 tức là lầu (hứng) được (ánh) trăng Vị trí Đền Ngọc Sơn trên bản đồ Việt Nam Đền Ngọc Sơn Thờ phụng Văn Xương Đế Quân Thánh tích chủ quản công danh và Hưng Đạo đại vương Trần Quốc Tuấn ? - 1300 Công trạng ba lần phá tan quân Nguyên-Mông Thông tin đền Đối tượng thờ thần và anh hùng dân tộc Địa chỉ quận Hoàn Kiếm, thành phố Hà Nội, Việt Nam Tọa độ 21°02′B 105°51′Đ / 21,03°B 105,85°Đ Thành lập thế kỷ 19 Người sáng lập Tín Trai Đền Ngọc Sơn là một ngôi đền thờ nằm trên đảo Ngọc của hồ Hoàn Kiếm ở Hà Nội, Việt Nam. Đây cũng là một di tích quốc gia đặc biệt của Việt Nam được xếp hạng đợt 4. Lịch sử","properties":{"Đền Ngọc Sơn":"Đền Ngọc Sơn","di tích quốc gia đặc biệt":"di tích quốc gia đặc biệt","Cổng đền Ngọc Sơn: trán cổng ghi ba chữ \"Đắc nguyệt lâu\" 得月樓 tức là lầu (hứng) được (ánh) trăng":"Cổng đền Ngọc Sơn: trán cổng ghi ba chữ \"Đắc nguyệt lâu\" 得月樓 tức là lầu (hứng) được (ánh) trăng","Vị trí Đền Ngọc Sơn trên bản đồ Việt Nam":"","Thờ phụng":"","Văn Xương Đế Quân":"Văn Xương Đế Quân","Thánh tích":"chủ quản công danh","và Hưng Đạo đại vương":"và; Hưng Đạo đại vương","Trần Quốc Tuấn":"Trần Quốc Tuấn","? - 1300":"? - 1300","Công trạng":"ba lần phá tan quân Nguyên-Mông","Thông tin đền":"","Đối tượng thờ":"thần và anh hùng dân tộc","Địa chỉ":"quận Hoàn Kiếm, thành phố Hà Nội, Việt Nam","Tọa độ":"21°02′B 105°51′Đ / 21,03°B 105,85°Đ","Thành lập":"thế kỷ 19","Người sáng lập":"Tín Trai"},"description":"Đền Ngọc Sơn là một ngôi đền thờ nằm trên đảo Ngọc của hồ Hoàn Kiếm ở Hà Nội, Việt Nam. Đây cũng là một di tích quốc gia đặc biệt của Việt Nam được xếp hạng đợt 4.\n\n\n","image":"image/6b1edb14-f80d-4a8b-801c-0965b482682e.png","source":"https://nguoikesu.com/dia-danh/den-ngoc-son"},{"name":"Đền Phù Đổng","allDocument":"Mục Lục [Thu / Mở] Kiến trúc Lễ hội Xem thêm Tham khảo Đền Phù Đổng Di tích quốc gia đặc biệt Cổng đền Phù Đổng Vị trí Đền Phù Đổng trên bản đồ Việt Nam Đền Phù Đổng Thờ phụng Phù Đổng Thiên Vương Thánh Gióng Công trạng Đánh đuổi giặc Ân Thông tin đền Địa chỉ xã Phù Đổng, huyện Gia Lâm, thành phố Hà Nội, Việt Nam Tọa độ 21°03′18″B 105°57′36″Đ / 21,055°B 105,96°Đ Người sáng lập Lý Thái Tổ Lễ hội 6 - 9 tháng 4 Âm lịch hàng năm Di tích đặc biệt Phân loại Di tích lịch sử, kiến trúc Thủy đình tại đền Phù Đổng nhìn từ đường đê xuống Thủy đình trước cổng đền Phù Đổng nhìn từ cổng đền Đền Phù Đổng hay còn gọi là đền Gióng thờ Thánh Gióng - Phù Đổng Thiên Vương, nằm ở xã Phù Đổng, Gia Lâm, ngoại thành Hà Nội. Toàn cảnh đền Phù Đồng từ trên cao Đền Phù Đổng còn được gọi là đền Thượng, tương truyền được dựng trên nền nhà cũ của Thánh Gióng, bên trong đê sông Đuống, còn đền Hạ thờ mẹ của Thánh Gióng nằm ngoài đê, gần nơi được cho là có dấu chân khổng lồ mà bà đã ướm thử rồi sinh ra Thánh Gióng. Năm 1010 khi rời đô về Thăng Long, Lý Thái Tổ đã cho dựng đền, đến nay đã được trùng tu nhiều lần. Kiến trúc","properties":{"Đền Phù Đổng":"Đền Phù Đổng","Di tích quốc gia đặc biệt":"Di tích quốc gia đặc biệt","Cổng đền Phù Đổng":"Cổng đền Phù Đổng","Vị trí Đền Phù Đổng trên bản đồ Việt Nam":"","Thờ phụng":"","Phù Đổng Thiên Vương":"Phù Đổng Thiên Vương","Thánh Gióng":"Thánh Gióng","Công trạng":"Đánh đuổi giặc Ân","Thông tin đền":"","Địa chỉ":"xã Phù Đổng, huyện Gia Lâm, thành phố Hà Nội, Việt Nam","Tọa độ":"21°03′18″B 105°57′36″Đ / 21,055°B 105,96°Đ","Người sáng lập":"Lý Thái Tổ","Lễ hội":"6 - 9 tháng 4 Âm lịch hàng năm","Di tích đặc biệt":"","Phân loại":"Di tích lịch sử, kiến trúc"},"description":"Đền Phù Đổng hay còn gọi là đền Gióng thờ Thánh Gióng - Phù Đổng Thiên Vương, nằm ở xã Phù Đổng, Gia Lâm, ngoại thành Hà Nội.\nĐền Phù Đổng còn được gọi là đền Thượng, tương truyền được dựng trên nền nhà cũ của Thánh Gióng, bên trong đê sông Đuống, còn đền Hạ thờ mẹ của Thánh Gióng nằm ngoài đê, gần nơi được cho là có dấu chân khổng lồ mà bà đã ướm thử rồi sinh ra Thánh Gióng. Năm 1010 khi rời đô về Thăng Long, Lý Thái Tổ đã cho dựng đền, đến nay đã được trùng tu nhiều lần.\n","image":"image/a81400d8-0b55-4100-8ea9-543a582f38b2.png","source":"https://nguoikesu.com/dia-danh/den-phu-dong"},{"name":"Đền Trần (Nam Định)","allDocument":"Mục Lục [Thu / Mở] Đền Thiên Trường Đền Cố Trạch Đền Trùng Hoa Lễ hội Đền Trần di tích quốc gia đặc biệt Cổng chính quần thể đền Trần Vị trí Đền Trần trên bản đồ Việt Nam Đền Trần Thờ phụng Hoàng thất nhà Trần Thông tin đền Địa chỉ phường Lộc Vượng, thành phố Nam Định, tỉnh Nam Định, Việt Nam Tọa độ 20°28′B 106°10′Đ / 20,46°B 106,17°Đ / 20.46; 106.17 Thành lập 1695 Lễ hội 15 - 20 tháng 8 âm lịch Đối với các định nghĩa khác, xem Đền Trần. Đền Trần (陳廟 - Trần Miếu) là một quần thể đền thờ tại đường Trần Thừa, phường Lộc Vượng, thành phố Nam Định (sát quốc lộ 10), là nơi thờ các vua nhà Trần cùng các quan lại có công phù tá nhà Trần. Đền Trần được xây dựng từ năm 1695, trên nền Thái miếu cũ của nhà Trần đã bị quân Minh phá hủy vào thế kỷ 15. Đền Trần bao gồm 3 công trình kiến trúc chính là đền Thiên Trường (hay đền Thượng), đền Cố Trạch (hay đền Hạ) và đền Trùng Hoa. Trước khi vào đền, phải qua hệ thống cổng ngũ môn. Trên cổng ghi các chữ Hán Chính nam môn (正南門 - cổng chính phía nam) và Trần Miếu (陳廟 - Miếu thờ nhà Trần). Qua cổng là một hồ nước hình chữ nhật. Chính giữa phía sau hồ nước là khu đền Thiền Trường. Phía Tây đền Thiên Trường là đền Trùng Hoa, phía Đông là đền Cố Trạch. Cả ba đền đều có kiến trúc chung, và quy mô ngang nhau. Mỗi đền gồm tòa tiền đường 5 gian, tòa trung đường 5 gian và tòa chính tẩm 3 gian. Nối tiền đường và trung đường là kinh đàn (thiêu hương) và 2 gian tả hữu. Đền Thiên Trường","properties":{"Đền Trần":"Đền Trần","di tích quốc gia đặc biệt":"di tích quốc gia đặc biệt","Cổng chính quần thể đền Trần":"Cổng chính quần thể đền Trần","Vị trí Đền Trần trên bản đồ Việt Nam":"","Thờ phụng":"","Hoàng thất nhà Trần":"Hoàng thất nhà Trần","Thông tin đền":"","Địa chỉ":"phường Lộc Vượng, thành phố Nam Định, tỉnh Nam Định, Việt Nam","Tọa độ":"20°28′B 106°10′Đ / 20,46°B 106,17°Đ / 20.46; 106.17","Thành lập":"1695","Lễ hội":"15 - 20 tháng 8 âm lịch"},"description":"Đền Trần (陳廟 - Trần Miếu) là một quần thể đền thờ tại đường Trần Thừa, phường Lộc Vượng, thành phố Nam Định (sát quốc lộ 10), là nơi thờ các vua nhà Trần cùng các quan lại có công phù tá nhà Trần. Đền Trần được xây dựng từ năm 1695, trên nền Thái miếu cũ của nhà Trần đã bị quân Minh phá hủy vào thế kỷ 15.\nĐền Trần bao gồm 3 công trình kiến trúc chính là đền Thiên Trường (hay đền Thượng), đền Cố Trạch (hay đền Hạ) và đền Trùng Hoa. Trước khi vào đền, phải qua hệ thống cổng ngũ môn. Trên cổng ghi các chữ Hán Chính nam môn (正南門 - cổng chính phía nam) và Trần Miếu (陳廟 - Miếu thờ nhà Trần). Qua cổng là một hồ nước hình chữ nhật. Chính giữa phía sau hồ nước là khu đền Thiền Trường. Phía Tây đền Thiên Trường là đền Trùng Hoa, phía Đông là đền Cố Trạch.\nCả ba đền đều có kiến trúc chung, và quy mô ngang nhau. Mỗi đền gồm tòa tiền đường 5 gian, tòa trung đường 5 gian và tòa chính tẩm 3 gian. Nối tiền đường và trung đường là kinh đàn (thiêu hương) và 2 gian tả hữu.\n\n\n","image":"image/97ecfdfb-baf2-4a4f-bbcd-e8b9852793cc.png","source":"https://nguoikesu.com/dia-danh/den-tran-nam-dinh"},{"name":"Đền Trần (Thái Bình)","allDocument":"Mục Lục [Thu / Mở] Lịch sử Vị trí Tổng quan kiến trúc Lễ hội đền Trần Đền Trần Di tích quốc gia đặc biệt Thờ phụng Hoàng thất nhà Trần Thông tin đền Địa chỉ làng Tam Đường, xã Tiến Đức, huyện Hưng Hà, tỉnh Thái Bình, Việt Nam Người sáng lập Hoàng tộc nhà Trần Đối với các định nghĩa khác, xem Đền Trần. Lễ hội đền Trần Lễ hội đền Trần Đền Trần Thái Bình là một quần thể di tích gồm các đền thờ, lăng mộ thờ các vị vua quan nhà Trần. Đền thờ các vua Trần trên đất phát tích Thái Bình (còn gọi là Thái Đường Lăng) thuộc làng Tam Đường, xã Tiến Đức, huyện Hưng Hà. Hệ thống các di tích lịch sử ở đây gồm Khu lăng mộ và đền thờ các vị vua triều Trần đều đã được chính phủ Việt Nam xếp hạng di tích quốc gia đặc biệt quan trọng. Lịch sử","properties":{"Đền Trần":"","Di tích quốc gia đặc biệt":"Di tích quốc gia đặc biệt","Thờ phụng":"","Hoàng thất nhà Trần":"Hoàng thất nhà Trần","Thông tin đền":"","Địa chỉ":"làng Tam Đường, xã Tiến Đức, huyện Hưng Hà, tỉnh Thái Bình, Việt Nam","Người sáng lập":"Hoàng tộc nhà Trần"},"description":"Đền Trần Thái Bình là một quần thể di tích gồm các đền thờ, lăng mộ thờ các vị vua quan nhà Trần. Đền thờ các vua Trần trên đất phát tích Thái Bình (còn gọi là Thái Đường Lăng) thuộc làng Tam Đường, xã Tiến Đức, huyện Hưng Hà. Hệ thống các di tích lịch sử ở đây gồm Khu lăng mộ và đền thờ các vị vua triều Trần đều đã được chính phủ Việt Nam xếp hạng di tích quốc gia đặc biệt quan trọng.\n\n\n","image":"image/3add5004-00c4-4d1f-8582-4404492a02da.png","source":"https://nguoikesu.com/dia-danh/den-tran-thai-binh"},{"name":"Hồ Hoàn Kiếm","allDocument":"Mục Lục [Thu / Mở] Vị trí Lịch sử Truyền thuyết Di tích liên quan Hệ sinh vật hồ Rùa Cảm hứng nghệ thuật Thơ văn Âm nhạc Nhiếp ảnh Hội họa Xem thêm Chú thích Hoàn Kiếm Hồ Hoàn Kiếm, Hà Nội. Địa lý Khu vực quận Hoàn Kiếm, Hà Nội Tọa độ 21°01′44″B 105°51′9″Đ / 21,02889°B 105,8525°Đ Kiểu hồ Nước ngọt Quốc gia lưu vực Việt Nam Độ dài tối đa 700 m Độ rộng tối đa 250 m Chu vi 1.750 m Diện tích bề mặt 12 ha Độ sâu trung bình 1-1,4 m Khu dân cư Hà Nội Hồ Hoàn Kiếm còn được gọi là Hồ Gươm (trong bản đồ Hà Nội năm 1886, hồ này được gọi là Hồ Hoàn Gươm - Lac de Hoan Guom), là một hồ nước ngọt tự nhiên của thành phố Hà Nội. Hồ có diện tích khoảng 12 ha . Trước kia, hồ còn có các tên gọi là hồ Lục Thủy (vì nước có màu xanh quanh năm), hồ Thủy Quân (dùng để duyệt thủy binh), hồ Tả Vọng và Hữu Vọng (trong thời Lê mạt). Tên gọi Hoàn Kiếm xuất hiện vào đầu thế kỷ 15 gắn với truyền thuyết vua Lê Lợi trả gươm báu cho Rùa thần. Tên hồ được lấy để đặt cho một quận trung tâm của Hà Nội (quận Hoàn Kiếm) và là hồ nước duy nhất của quận này cho đến ngày nay. Vị trí","properties":{"Hoàn Kiếm":"","Hồ Hoàn Kiếm, Hà Nội.":"Hồ Hoàn Kiếm, Hà Nội.","Địa lý":"","Khu vực":"quận Hoàn Kiếm, Hà Nội","Tọa độ":"21°01′44″B 105°51′9″Đ / 21,02889°B 105,8525°Đ","Kiểu hồ":"Nước ngọt","Quốc gia lưu vực":"Việt Nam","Độ dài tối đa":"700 m","Độ rộng tối đa":"250 m","Chu vi":"1.750 m","Diện tích bề mặt":"12 ha","Độ sâu trung bình":"1-1,4 m","Khu dân cư":"Hà Nội"},"description":"Hồ Hoàn Kiếm còn được gọi là Hồ Gươm (trong bản đồ Hà Nội năm 1886, hồ này được gọi là Hồ Hoàn Gươm - Lac de Hoan Guom), là một hồ nước ngọt tự nhiên của thành phố Hà Nội. Hồ có diện tích khoảng 12 ha . Trước kia, hồ còn có các tên gọi là hồ Lục Thủy (vì nước có màu xanh quanh năm), hồ Thủy Quân (dùng để duyệt thủy binh), hồ Tả Vọng và Hữu Vọng (trong thời Lê mạt). Tên gọi Hoàn Kiếm xuất hiện vào đầu thế kỷ 15 gắn với truyền thuyết vua Lê Lợi trả gươm báu cho Rùa thần. Tên hồ được lấy để đặt cho một quận trung tâm của Hà Nội (quận Hoàn Kiếm) và là hồ nước duy nhất của quận này cho đến ngày nay.\n\n\n","image":"image/77307011-2e38-4eb2-a9bb-a3342c555fb5.png","source":"https://nguoikesu.com/dia-danh/ho-hoan-kiem"},{"name":"Khu di tích chiến thắng Điện Biên Phủ","properties":{},"description":"Khu di tích chiến trường Ðiện Biên Phủ là một quần thể các di tích lịch sử ghi lại chiến công của quân và dân Việt Nam trong cuộc kháng chiến anh dũng chống thực dân Pháp xâm lược. Hiện nay, nơi đây đã được thủ tướng chính phủ Việt Nam đưa vào danh sách xếp hạng 23 di tích quốc gia đặc biệt.\nCác di tích nổi bật của chiến trường Ðiện Biên năm xưa là đồi A1, C1, C2, D1, cứ điểm Hồng Cúm, Him Lam, đồi Ðộc Lập, cầu và sân bay Mường Thanh, hầm chỉ huy của tướng Ðờ Catri.\n\n\n","image":"image/91878194-c2d2-4346-9ee7-250860184adb.png","allDocument":"Mục Lục [Thu / Mở] Đồi A1 Hầm chỉ huy tướng Đờ Cát Sở chỉ huy chiến dịch Điện Biên Phủ Bảo tàng chiến thắng Điện Biên Phủ Tham khảo Đài tưởng niệm chiến thắng Điện Biên Phủ Khu di tích chiến trường Ðiện Biên Phủ là một quần thể các di tích lịch sử ghi lại chiến công của quân và dân Việt Nam trong cuộc kháng chiến anh dũng chống thực dân Pháp xâm lược. Hiện nay, nơi đây đã được thủ tướng chính phủ Việt Nam đưa vào danh sách xếp hạng 23 di tích quốc gia đặc biệt. Các di tích nổi bật của chiến trường Ðiện Biên năm xưa là đồi A1, C1, C2, D1, cứ điểm Hồng Cúm, Him Lam, đồi Ðộc Lập, cầu và sân bay Mường Thanh, hầm chỉ huy của tướng Ðờ Catri. Đồi A1","source":"https://nguoikesu.com/dia-danh/khu-di-tich-chien-thang-dien-bien-phu"},{"name":"Khu di tích Chủ tịch Hồ Chí Minh tại Phủ Chủ tịch","properties":{},"description":"Khu di tích Chủ tịch Hồ Chí Minh tại Phủ Chủ tịch, gọi tắt là Khu di tích Phủ Chủ tịch tại Hà Nội, là nơi sống và làm việc lâu nhất của Hồ Chí Minh (từ 19 tháng 12 năm 1954 đến 2 tháng 9 năm 1969), được Bộ Văn hóa Thông tin ra Quyết định xếp hạng là Khu di tích ngày 15 tháng 5 năm 1975. Hiện nay, nơi đây đã được thủ tướng chính phủ Việt Nam đưa vào danh sách xếp hạng 23 di tích quốc gia đặc biệt.\nKhu đất này nguyên là phần đất phía tây bắc của Hoàng thành thuộc Kinh thành Thăng Long xưa. Khi Pháp xâm lược Việt Nam, sau khi chiếm xong miền Bắc đã chọn Hà Nội làm trung tâm đầu não cho toàn bộ Đông Dương và Phủ toàn quyền Đông Dương được xây dựng trên mảnh đất này. Sau khi cuộc kháng chiến chống Pháp kết thúc, nơi này được chọn là nơi làm việc của Đảng Cộng sản Việt Nam và Nhà nước, đồng thời là nơi sống và làm việc của Chủ tịch Hồ Chí Minh. Nơi đây cũng là nơi Hồ Chí Minh đã qua đời.\nTại Phủ Chủ tịch, Chủ tịch Hồ Chí Minh đã từng gặp nhiều đoàn khách là đại biểu của các chính đảng, đoàn thể, tôn giáo; đại biểu của công nhân, nông dân, trí thức, quân đội; đại biểu của các dân tộc thiểu số; đại biểu của người dân Miền Nam Việt Nam và quân nhân thuộc Quân Giải phóng Miền Nam Việt Nam (ở Việt Nam gọi tắt là \"đồng bào chiến sĩ miền Nam\")\nCũng tại nơi đây, ông còn tiếp những người là đại biểu những người Việt sống ở nước ngoài về thăm Việt Nam; đại biểu của các đội thiếu niên, đoàn thanh niên, hội phụ nữ...\nNgày 9 tháng 2 năm 1955, cửa Phủ Chủ tịch đã mở cho các thiếu niên đến vui chơi, từ đó các thiếu nhi có nhiều dịp được vào đây thăm ông. Ông còn tổ chức nhiều triển lãm tranh thiếu nhi tại đây.\nSau khi Chủ tịch Hồ Chí Minh qua đời, khu Phủ Chủ tịch trở thành khu di tích lịch sử. Nhiều khách du lịch tại Việt Nam và khắp thế giới đến thăm khu di tích này.\nKhi Viện Bảo tàng Hồ Chí Minh được thành lập ngày 12 tháng 9 năm 1977, khu này nằm dưới sự quản lý của Bảo tàng Hồ Chí Minh. Ngày 6 tháng 11 năm 1992, Khu di tích Phủ Chủ tịch được tách ra khỏi Bảo tàng Hồ Chí Minh và trực thuộc Bộ Văn hóa Thông tin.\nTổng thể khu di tích rộng hơn 14 hécta, trong đó diện tích được xếp hạng là 22.000 m², bao gồm 16 công trình, công trình đã tồn tại lâu nhất là hơn 100 năm và gần nhất là hơn 40 năm. Một số công trình có giá trị lớn trong khu di tích:\nNgoài ra, khu vườn tại đây có 161 loài thực vật thuộc 54 họ thực vật, trong đó có 58 loài có nguồn gốc nước ngoài.\n","image":null,"allDocument":"Mục Lục [Thu / Mở] Chú thích Xem thêm Nhà sàn nơi Chủ tịch nước Hồ Chí Minh làm việc tại Phủ Chủ tịch Khu di tích Chủ tịch Hồ Chí Minh tại Phủ Chủ tịch, gọi tắt là Khu di tích Phủ Chủ tịch tại Hà Nội, là nơi sống và làm việc lâu nhất của Hồ Chí Minh (từ 19 tháng 12 năm 1954 đến 2 tháng 9 năm 1969), được Bộ Văn hóa Thông tin ra Quyết định xếp hạng là Khu di tích ngày 15 tháng 5 năm 1975. Hiện nay, nơi đây đã được thủ tướng chính phủ Việt Nam đưa vào danh sách xếp hạng 23 di tích quốc gia đặc biệt. Khu đất này nguyên là phần đất phía tây bắc của Hoàng thành thuộc Kinh thành Thăng Long xưa. Khi Pháp xâm lược Việt Nam, sau khi chiếm xong miền Bắc đã chọn Hà Nội làm trung tâm đầu não cho toàn bộ Đông Dương và Phủ toàn quyền Đông Dương được xây dựng trên mảnh đất này. Sau khi cuộc kháng chiến chống Pháp kết thúc, nơi này được chọn là nơi làm việc của Đảng Cộng sản Việt Nam và Nhà nước, đồng thời là nơi sống và làm việc của Chủ tịch Hồ Chí Minh. Nơi đây cũng là nơi Hồ Chí Minh đã qua đời. Tại Phủ Chủ tịch, Chủ tịch Hồ Chí Minh đã từng gặp nhiều đoàn khách là đại biểu của các chính đảng, đoàn thể, tôn giáo; đại biểu của công nhân, nông dân, trí thức, quân đội; đại biểu của các dân tộc thiểu số; đại biểu của người dân Miền Nam Việt Nam và quân nhân thuộc Quân Giải phóng Miền Nam Việt Nam (ở Việt Nam gọi tắt là \"đồng bào chiến sĩ miền Nam\") Cũng tại nơi đây, ông còn tiếp những người là đại biểu những người Việt sống ở nước ngoài về thăm Việt Nam; đại biểu của các đội thiếu niên, đoàn thanh niên, hội phụ nữ... Ngày 9 tháng 2 năm 1955, cửa Phủ Chủ tịch đã mở cho các thiếu niên đến vui chơi, từ đó các thiếu nhi có nhiều dịp được vào đây thăm ông. Ông còn tổ chức nhiều triển lãm tranh thiếu nhi tại đây. Nhà họp Bộ Chính trị tại Phủ Chủ tịch. Sau khi Chủ tịch Hồ Chí Minh qua đời, khu Phủ Chủ tịch trở thành khu di tích lịch sử. Nhiều khách du lịch tại Việt Nam và khắp thế giới đến thăm khu di tích này. Khi Viện Bảo tàng Hồ Chí Minh được thành lập ngày 12 tháng 9 năm 1977, khu này nằm dưới sự quản lý của Bảo tàng Hồ Chí Minh. Ngày 6 tháng 11 năm 1992, Khu di tích Phủ Chủ tịch được tách ra khỏi Bảo tàng Hồ Chí Minh và trực thuộc Bộ Văn hóa Thông tin. Tổng thể khu di tích rộng hơn 14 hécta, trong đó diện tích được xếp hạng là 22.000 m², bao gồm 16 công trình, công trình đã tồn tại lâu nhất là hơn 100 năm và gần nhất là hơn 40 năm. Một số công trình có giá trị lớn trong khu di tích: \"Nhà sàn Bác Hồ\": phục chế theo nhà sàn, nơi Chủ tịch Hồ Chí Minh đã ở từ ngày 18 tháng 5 năm 1958 đến ngày 17 tháng 8 năm 1969. Ngôi nhà sàn này được dựng lại theo nguyên mẫu năm 1969, sau khi Chủ tịch Hồ Chí Minh qua đời. Năm 1969, Bảo tàng Hồ Chí Minh đã mua gỗ về làm một ngôi nhà sàn đồng dạng dựng trên nền cũ tại Hà Nội, còn nhà sàn gốc được cất giữ bảo quản trong kho . Nhà 54, nơi Chủ tịch Hồ Chí Minh đã ở và làm việc từ ngày 19 tháng 12 năm 1954 đến ngày 18 tháng 5 năm 1958. Sau khi chuyển về sống ở Nhà sàn, hàng ngày ông vẫn đến đây ăn cơm và sử dụng các phương tiện vệ sinh cá nhân. Phòng họp Bộ Chính trị, nơi quyết định cuộc Tấn công và nổi dậy Xuân 1968. Nhà 67, nơi họp Bộ Chính trị, cũng là nơi Hồ Chí Minh dưỡng bệnh và qua đời. Giàn hoa Phủ Chủ tịch, nơi Hồ Chí Minh thường tiếp khách. Nhà bếp A và nhà bếp B. Nhà Thủ tướng. Nhà ký sắc lệnh. Đường Xoài: con đường mà Chủ tịch Hồ Chí Minh thường đi bách bộ sau giờ làm việc và tập thể dục buổi sáng. \"Đường mòn Bác Hồ\": con đường mà Chủ tịch Hồ Chí Minh luyện tập với mong muốn có đủ sức vào thăm người dân miền Nam Việt Nam trong những năm cuối đời. \"Ao cá Bác Hồ\" với diện tích 3.320 m², sâu 3 m, có nhiều loài cá được thả tại đây. Ngoài ra, khu vườn tại đây có 161 loài thực vật thuộc 54 họ thực vật, trong đó có 58 loài có nguồn gốc nước ngoài. Chú thích","source":"https://nguoikesu.com/dia-danh/khu-di-tich-chu-tich-ho-chi-minh-tai-phu-chu-tich"},{"name":"Khu di tích Pác Bó","properties":{},"description":"Khu di tích Pác Bó là một khu di tích lịch sử cách mạng quốc gia - đặc biệt của Việt Nam, thuộc bản Pác Bó xã Trường Hà huyện Hà Quảng tỉnh Cao Bằng , cách thành phố Cao Bằng 55 km về phía Bắc. Khu di tích bao gồm: nhà tưởng niệm Bác Hồ, hang Cốc Pó(tên địa phương có nghĩa là \"đầu nguồn\" ), hang Lũng Lạn, hang Ngườm Vài (đều trên núi Các Mác), suối Lê nin, bàn đá nơi Bác Hồ làm việc, nền nhà ông Lý Quốc Súng, nền nhà ông La Thành, v.v...\nNgày 8 tháng 2 năm 1941, khi về nước, Hồ Chí Minh đã sống và làm việc trong hang Cốc Bó và đặt tên dòng suối trước cửa hang là \"suối Lênin\" và ngọn núi có hang này là \"núi Các Mác\". Trước năm 1979 hang Cốc Pó rộng khoảng 15m³, trước cửa hang có một con suối lớn chảy ngầm từ trong núi đá ra, nguồn của con suối là bên phía Bắc của ngọn núi này và thuộc lãnh thổ Trung Quốc. Trong chiến tranh biên giới Việt-Trung năm 1979, quân Trung Quốc đã cho nổ mìn phá hoại hang Cốc Pó . Ngày nay, hang Cốc Pó được khôi phục một phần để phục vụ khách tham quan du lịch.\n","image":"image/51950f98-6f47-4226-a440-ed92acaab81d.png","allDocument":"Sơ đồ danh sách các di tích quốc gia đặc biệt ở Việt Nam Khu di tích Pác Bó là một khu di tích lịch sử cách mạng quốc gia - đặc biệt của Việt Nam, thuộc bản Pác Bó xã Trường Hà huyện Hà Quảng tỉnh Cao Bằng , cách thành phố Cao Bằng 55 km về phía Bắc. Khu di tích bao gồm: nhà tưởng niệm Bác Hồ, hang Cốc Pó(tên địa phương có nghĩa là \"đầu nguồn\" ), hang Lũng Lạn, hang Ngườm Vài (đều trên núi Các Mác), suối Lê nin, bàn đá nơi Bác Hồ làm việc, nền nhà ông Lý Quốc Súng, nền nhà ông La Thành, v.v... Ngày 8 tháng 2 năm 1941, khi về nước, Hồ Chí Minh đã sống và làm việc trong hang Cốc Bó và đặt tên dòng suối trước cửa hang là \"suối Lênin\" và ngọn núi có hang này là \"núi Các Mác\". Trước năm 1979 hang Cốc Pó rộng khoảng 15m³, trước cửa hang có một con suối lớn chảy ngầm từ trong núi đá ra, nguồn của con suối là bên phía Bắc của ngọn núi này và thuộc lãnh thổ Trung Quốc. Trong chiến tranh biên giới Việt-Trung năm 1979, quân Trung Quốc đã cho nổ mìn phá hoại hang Cốc Pó . Ngày nay, hang Cốc Pó được khôi phục một phần để phục vụ khách tham quan du lịch. Chú thích","source":"https://nguoikesu.com/dia-danh/khu-di-tich-pac-bo"},{"name":"Khu lăng mộ và đền thờ các vị vua triều Lý","allDocument":"Mục Lục [Thu / Mở] Khái quát Kiến trúc Hội Đền Chú giải Nguồn tư liệu Đền Lý Bát Đế Di tích quốc gia đặc biệt Chính điện ở Đền Đô Thờ phụng Tám vua nhà Lý Thông tin đền Địa chỉ khu Phố Thượng, phường Đình Bảng, thị xã Từ Sơn, tỉnh Bắc Ninh, Việt Nam Thành lập 3 tháng 3, 1030 Người sáng lập Lý Thái Tông Tôn tạo 1602 Xây mới 1989 Lễ hội 14, 15, 16 tháng 3 âm lịch hàng năm Đền Lý Bát Đế, còn gọi là Đền Đô hoặc Cổ Pháp điện là một quần thể kiến trúc tín ngưỡng thờ tám vị vua đầu tiên của nhà Lý. Đền Lý Bát Đế đã được Nhà nước Việt Nam công nhận là di tích lịch sử - văn hóa theo Quyết định số 154 của Bộ Văn hóa - Thông tin (nay là Bộ Văn hóa, Thể thao và Du lịch) ngày 25 tháng 1 năm 1991. Năm 2014, nơi đây cùng với khu lăng mộ các Vua nhà Lý đã được xếp hạng di tích quốc gia đặc biệt. Khái quát","properties":{"Đền Lý Bát Đế":"","Di tích quốc gia đặc biệt":"Di tích quốc gia đặc biệt","Chính điện ở Đền Đô":"Chính điện ở Đền Đô","Thờ phụng":"","Tám vua nhà Lý":"Tám vua nhà Lý","Thông tin đền":"","Địa chỉ":"khu Phố Thượng, phường Đình Bảng, thị xã Từ Sơn, tỉnh Bắc Ninh, Việt Nam","Thành lập":"3 tháng 3, 1030","Người sáng lập":"Lý Thái Tông","Tôn tạo":"1602","Xây mới":"1989","Lễ hội":"14, 15, 16 tháng 3 âm lịch hàng năm"},"description":"Đền Lý Bát Đế, còn gọi là Đền Đô hoặc Cổ Pháp điện là một quần thể kiến trúc tín ngưỡng thờ tám vị vua đầu tiên của nhà Lý. Đền Lý Bát Đế đã được Nhà nước Việt Nam công nhận là di tích lịch sử - văn hóa theo Quyết định số 154 của Bộ Văn hóa - Thông tin (nay là Bộ Văn hóa, Thể thao và Du lịch) ngày 25 tháng 1 năm 1991. Năm 2014, nơi đây cùng với khu lăng mộ các Vua nhà Lý đã được xếp hạng di tích quốc gia đặc biệt.\n\n\n","image":"image/79448468-ebd8-452f-a712-4766d43a0c8c.png","source":"https://nguoikesu.com/dia-danh/khu-lang-mo-va-den-tho-cac-vi-vua-trieu-ly"},{"name":"Khu lưu niệm Chủ tịch Tôn Đức Thắng","properties":{},"description":"Khu lưu niệm Chủ tịch Tôn Đức Thắng tọa lạc trên cù lao Ông Hổ, thuộc xã Mỹ Hòa Hưng, thành phố Long Xuyên, tỉnh An Giang. Đây là một trong số 23 di tích Việt Nam đã được xếp hạng di tích quốc gia đặc biệt (ký ngày 10 tháng 5 năm 2012, công bố ngày 17 tháng 7 năm 2012).\n\n\n","image":null,"allDocument":"Mục Lục [Thu / Mở] Giới thiệu Ngôi nhà thời niên thiếu Khu đền thờ và nhà trưng bày Ảnh Xem thêm Chú thích Sơ đồ danh sách các di tích quốc gia đặc biệt ở Việt Nam Khu lưu niệm Chủ tịch Tôn Đức Thắng tọa lạc trên cù lao Ông Hổ, thuộc xã Mỹ Hòa Hưng, thành phố Long Xuyên, tỉnh An Giang. Đây là một trong số 23 di tích Việt Nam đã được xếp hạng di tích quốc gia đặc biệt (ký ngày 10 tháng 5 năm 2012, công bố ngày 17 tháng 7 năm 2012). Giới thiệu","source":"https://nguoikesu.com/dia-danh/khu-luu-niem-chu-tich-ton-duc-thang"},{"name":"Quần thể di tích Cố đô Huế","allDocument":"Mục Lục [Thu / Mở] Di sản văn hoá thế giới Cố Đô Huế Kinh thành Huế Hoàng thành Huế Tử cấm thành Các di tích ngoài kinh thành Lăng tẩm Các di tích khác Tham khảo Xem thêm Quần thể di tích Cố đô Huế Di sản thế giới UNESCO Quốc gia Việt Nam Kiểu Văn hóa Hạng mục IV Tham khảo 678 Vùng UNESCO Châu Á-Thái Bình Dương Lịch sử công nhận Công nhận 1993 (kì thứ 17) Quần thể di tích Cố đô Huế hay Quần thể di tích Huế là những di tích lịch sử - văn hoá do triều Nguyễn chủ trương xây dựng trong khoảng thời gian từ đầu thế kỷ 19 đến nửa đầu thế kỷ 20 trên địa bàn kinh đô Huế xưa; nay thuộc phạm vi thành phố Huế và một vài vùng phụ cận thuộc tỉnh Thừa Thiên-Huế, Việt Nam. Phần lớn các di tích này nay thuộc sự quản lý của Trung tâm Bảo tồn Di tích Cố đô Huế và được UNESCO công nhận là Di sản Văn hoá Thế giới vào ngày 11 tháng 12 năm 1993. Hiện tại, cố đô Huế đã được thủ tướng chính phủ Việt Nam đưa vào danh sách xếp hạng 62 di tích quốc gia đặc biệt quan trọng. Quần thể di tích Cố đô Huế có thể phân chia thành các cụm công trình gồm các cụm công trình ngoài Kinh thành Huế và trong kinh thành Huế. Di sản văn hoá thế giới Cố Đô Huế","properties":{"Quần thể di tích Cố đô Huế":"","Di sản thế giới UNESCO":"Di sản thế giới UNESCO","Quốc gia":"Việt Nam","Kiểu":"Văn hóa","Hạng mục":"IV","Tham khảo":"678","Vùng UNESCO":"Châu Á-Thái Bình Dương","Lịch sử công nhận":"","Công nhận":"1993 (kì thứ 17)"},"description":"Quần thể di tích Cố đô Huế hay Quần thể di tích Huế là những di tích lịch sử - văn hoá do triều Nguyễn chủ trương xây dựng trong khoảng thời gian từ đầu thế kỷ 19 đến nửa đầu thế kỷ 20 trên địa bàn kinh đô Huế xưa; nay thuộc phạm vi thành phố Huế và một vài vùng phụ cận thuộc tỉnh Thừa Thiên-Huế, Việt Nam. Phần lớn các di tích này nay thuộc sự quản lý của Trung tâm Bảo tồn Di tích Cố đô Huế và được UNESCO công nhận là Di sản Văn hoá Thế giới vào ngày 11 tháng 12 năm 1993. Hiện tại, cố đô Huế đã được thủ tướng chính phủ Việt Nam đưa vào danh sách xếp hạng 62 di tích quốc gia đặc biệt quan trọng. Quần thể di tích Cố đô Huế có thể phân chia thành các cụm công trình gồm các cụm công trình ngoài Kinh thành Huế và trong kinh thành Huế.\n\n\n","image":null,"source":"https://nguoikesu.com/dia-danh/quan-the-di-tich-co-do-hue"},{"name":"Quần thể di tích danh thắng Yên Tử","properties":{},"description":"Quần thể di tích và danh thắng Yên Tử bao gồm một hệ thống các di tích lịch sử văn hóa gắn liền với sự ra đời, hình thành và phát triển của thiền phái Trúc Lâm ở Việt Nam. Các di tích này nằm ở khu vực giáp ranh giữa 3 tỉnh Bắc Giang, Hải Dương và Quảng Ninh, bao gồm 5 khu vực: Khu di tích và danh thắng Đông Yên Tử (TP Uông Bí, Quảng Ninh), Khu di tích lịch sử nhà Trần (Đông Triều, Quảng Ninh), Khu di tích và danh thắng Tây Yên Tử (nằm trên các huyện Yên Dũng, Lục Nam, Lục Ngạn, Sơn Động tỉnh Bắc Giang) , Khu di tích Côn Sơn - Kiếp Bạc – Thanh Mai (Chí Linh, tỉnh Hải Dương).\nHiện nay, Bộ Văn hóa, Thể thao và Du lịch (Việt Nam) đang triển khai việc phối hợp với UBND các tỉnh Bắc Giang, Hải Dương và Quảng Ninh lập hồ sơ di tích - danh thắng Yên Tử đệ trình Tổ chức Giáo dục, Khoa học và Văn hóa của Liên hiệp quốc UNESCO xem xét, công nhận là Di sản thế giới. Đây có thể là di sản thế giới liên tỉnh đầu tiên ở Việt Nam.\n\n\n","image":"image/ba51f5f8-f576-4741-b26f-1f0140e081e6.png","allDocument":"Mục Lục [Thu / Mở] Tổng quan Các khu di tích Khu di tích lịch sử nhà Trần Khu di tích Tây Yên Tử Khu di tích Đông Yên Tử Khu di tích Côn Sơn - Kiếp Bạc - Thanh Mai Khu di tích lịch sử Bạch Đằng Ứng cử di sản thế giới Tiêu chí nổi bật toàn cầu Tham khảo Quần thể di tích và danh thắng Yên Tử bao gồm một hệ thống các di tích lịch sử văn hóa gắn liền với sự ra đời, hình thành và phát triển của thiền phái Trúc Lâm ở Việt Nam. Các di tích này nằm ở khu vực giáp ranh giữa 3 tỉnh Bắc Giang, Hải Dương và Quảng Ninh, bao gồm 5 khu vực: Khu di tích và danh thắng Đông Yên Tử (TP Uông Bí, Quảng Ninh), Khu di tích lịch sử nhà Trần (Đông Triều, Quảng Ninh), Khu di tích và danh thắng Tây Yên Tử (nằm trên các huyện Yên Dũng, Lục Nam, Lục Ngạn, Sơn Động tỉnh Bắc Giang) , Khu di tích Côn Sơn - Kiếp Bạc – Thanh Mai (Chí Linh, tỉnh Hải Dương). Hiện nay, Bộ Văn hóa, Thể thao và Du lịch (Việt Nam) đang triển khai việc phối hợp với UBND các tỉnh Bắc Giang, Hải Dương và Quảng Ninh lập hồ sơ di tích - danh thắng Yên Tử đệ trình Tổ chức Giáo dục, Khoa học và Văn hóa của Liên hiệp quốc UNESCO xem xét, công nhận là Di sản thế giới. Đây có thể là di sản thế giới liên tỉnh đầu tiên ở Việt Nam. Khách thập phương lên núi Yên Tử Tổng quan","source":"https://nguoikesu.com/dia-danh/quan-the-di-tich-danh-thang-yen-tu"},{"name":"thành Cổ Loa","properties":{},"description":"Cổ Loa là kinh đô của nhà nước Âu Lạc, dưới thời An Dương Vương vào khoảng thế kỷ thứ 3 trước Công nguyên và của nhà nước phong kiến dưới thời Ngô Quyền thế kỷ 10 sau Công nguyên.\nHiện nay, di tích Cổ Loa thuộc xã Cổ Loa, huyện Đông Anh, Hà Nội.\n\n\n","allDocument":"Mục Lục [Thu / Mở] Bối cảnh địa lý Xây dựng thành Cấu trúc Thành Cổ Loa Giá trị của thành Cổ Loa Di vật khảo cổ Văn hóa Phùng Nguyên (2000 - 1500 TCN) Văn hóa Đông Sơn (700 TCN - 100 SCN) Xem thêm Tham khảo Cổ Loa là kinh đô của nhà nước Âu Lạc, dưới thời An Dương Vương vào khoảng thế kỷ thứ 3 trước Công nguyên và của nhà nước phong kiến dưới thời Ngô Quyền thế kỷ 10 sau Công nguyên. Hiện nay, di tích Cổ Loa thuộc xã Cổ Loa, huyện Đông Anh, Hà Nội. Bối cảnh địa lý","source":"https://nguoikesu.com/dia-danh/thanh-co-loa"},{"name":"Thành cổ Quảng Trị","allDocument":"Mục Lục [Thu / Mở] Lịch sử Trận Cổ thành Quảng Trị 1972 Hiện nay Ảnh Chú thích Thành cổ Quảng Trị Vị trí Quảng Trị Diện tích 25 ha Chiều cao 4 m Xây dựng 1809 Tọa độ: 16°45′06″B 107°11′12″Đ / 16,751672°B 107,186772°Đ Thành cổ Quảng Trị hoặc Cổ thành Quảng Trị là một Di tích quốc gia đặc biệt của Việt Nam được xếp hạng đợt 4, tọa lạc ở trung tâm thị xã Quảng Trị, tỉnh Quảng Trị,. Lịch sử","properties":{"Thành cổ Quảng Trị":"","Vị trí":"Quảng Trị","Diện tích":"25 ha","Chiều cao":"4 m","Xây dựng":"1809"},"description":"Tọa độ: 16°45′06″B 107°11′12″Đ / 16,751672°B 107,186772°Đ\nThành cổ Quảng Trị hoặc Cổ thành Quảng Trị là một Di tích quốc gia đặc biệt của Việt Nam được xếp hạng đợt 4, tọa lạc ở trung tâm thị xã Quảng Trị, tỉnh Quảng Trị,.\n\n\n","image":"image/ad2028b9-3dbe-4ce8-89af-44b73d990250.png","source":"https://nguoikesu.com/dia-danh/thanh-co-quang-tri"},{"name":"Thành nhà Hồ","allDocument":"Mục Lục [Thu / Mở] Vị trí Đặc điểm Kích thước Theo các tài liệu Theo số liệu đo đạc Kết cấu Khu di tích thành nhà Hồ Tường thành và Hào thành La Thành Đàn Nam Giao Đền thờ nàng Bình Khương Đình Đông Môn Vấn đề công nhận và bảo tồn Hình ảnh Chú thích Thành nhà Hồ Di sản thế giới UNESCO Quốc gia Việt Nam Kiểu Văn hóa Hạng mục ii, iv Tham khảo 1358 Vùng UNESCO Châu Á-Thái Bình Dương Lịch sử công nhận Công nhận 2011 (kì thứ 35) Xem các mục từ khác có cùng tên \"Tây Đô\" tại Tây Đô. Tọa độ: 20°4′40″B 105°36′17″Đ / 20,07778°B 105,60472°Đ Thành nhà Hồ (hay còn gọi là thành Tây Đô, thành An Tôn, thành Tây Kinh hay thành Tây Giai) là kinh đô nước Đại Ngu (quốc hiệu Việt Nam thời nhà Hồ), nằm trên địa phận nay thuộc tỉnh Thanh Hóa. Đây là tòa thành kiên cố với kiến trúc độc đáo bằng đá có quy mô lớn hiếm hoi ở Việt Nam, có giá trị và độc đáo nhất, duy nhất còn lại ở Đông Nam Á và là một trong rất ít những thành lũy bằng đá còn lại trên thế giới . Thành được xây dựng trong thời gian ngắn, chỉ khoảng 3 tháng (từ tháng Giêng đến tháng 3 năm 1397) và cho đến nay, dù đã tồn tại hơn 6 thế kỷ nhưng một số đoạn của tòa thành này còn lại tương đối nguyên vẹn. Ngày 27 tháng 6 năm 2011, sau 6 năm đệ trình hồ sơ, Thành nhà Hồ đã được UNESCO công nhận là di sản văn hóa thế giới. Hiện nay, nơi đây đã được thủ tướng chính phủ Việt Nam đưa vào danh sách xếp hạng 62 di tích quốc gia đặc biệt. Vị trí","properties":{"Thành nhà Hồ":"","Di sản thế giới UNESCO":"Di sản thế giới UNESCO","Quốc gia":"Việt Nam","Kiểu":"Văn hóa","Hạng mục":"ii, iv","Tham khảo":"1358","Vùng UNESCO":"Châu Á-Thái Bình Dương","Lịch sử công nhận":"","Công nhận":"2011 (kì thứ 35)"},"description":"Tọa độ: 20°4′40″B 105°36′17″Đ / 20,07778°B 105,60472°Đ\nThành nhà Hồ (hay còn gọi là thành Tây Đô, thành An Tôn, thành Tây Kinh hay thành Tây Giai) là kinh đô nước Đại Ngu (quốc hiệu Việt Nam thời nhà Hồ), nằm trên địa phận nay thuộc tỉnh Thanh Hóa. Đây là tòa thành kiên cố với kiến trúc độc đáo bằng đá có quy mô lớn hiếm hoi ở Việt Nam, có giá trị và độc đáo nhất, duy nhất còn lại ở Đông Nam Á và là một trong rất ít những thành lũy bằng đá còn lại trên thế giới . Thành được xây dựng trong thời gian ngắn, chỉ khoảng 3 tháng (từ tháng Giêng đến tháng 3 năm 1397) và cho đến nay, dù đã tồn tại hơn 6 thế kỷ nhưng một số đoạn của tòa thành này còn lại tương đối nguyên vẹn.\nNgày 27 tháng 6 năm 2011, sau 6 năm đệ trình hồ sơ, Thành nhà Hồ đã được UNESCO công nhận là di sản văn hóa thế giới. Hiện nay, nơi đây đã được thủ tướng chính phủ Việt Nam đưa vào danh sách xếp hạng 62 di tích quốc gia đặc biệt.\n\n\n","image":null,"source":"https://nguoikesu.com/dia-danh/thanh-nha-ho"},{"name":"Văn Miếu - Quốc Tử Giám","properties":{},"description":"Văn Miếu - Quốc Tử Giám (chữ Hán:文廟 - 國子監) là quần thể di tích đa dạng và phong phú hàng đầu của thành phố Hà Nội, nằm ở phía Nam kinh thành Thăng Long. Hiện nay, nơi đây đã được thủ tướng chính phủ Việt Nam đưa vào danh sách xếp hạng 23 di tích quốc gia đặc biệt. Quần thể kiến trúc Văn Miếu - Quốc Tử Giám bao gồm: hồ Văn, khu Văn Miếu - Quốc Tử Giám và vườn Giám và kiến trúc chủ thể là Văn Miếu - nơi thờ Khổng Tử và Quốc Tử Giám - trường đại học đầu tiên của Việt Nam. Khu Văn Miếu - Quốc Tử Giám có tường gạch vồ bao quanh, phía trong chia thành 5 lớp không gian với các kiến trúc khác nhau. Mỗi lớp không gian đó được giới hạn bởi các tường gạch có 3 cửa để thông với nhau (gồm cửa chính giữa và hai cửa phụ hai bên). Từ ngoài vào trong có các cổng lần lượt là: cổng Văn Miếu, Đại Trung, Đại Thành và cổng Thái Học. Với hơn 700 năm hoạt động đã đào tạo hàng nghìn nhân tài cho đất nước. Ngày nay, Văn Miếu Quốc Tử Giám là nơi tham quan của du khách trong và ngoài nước đồng thời cũng là nơi khen tặng cho học sinh xuất sắc và còn là nơi tổ chức hội thơ hàng năm vào ngày rằm tháng giêng. Đây từng là nơi các sĩ tử đến \"cầu may\" trước mỗi kỳ thi bằng cách vuốt đầu rùa tại các bia tiến sĩ, tuy nhiên, ngày nay, để bảo tồn di tích, một hàng rào được thiết lập và các sĩ tử không còn làm nghi thức cầu may như trước nữa.Nơi này là nơi trên tờ tiền polymer 100.000 VND của Việt Nam\n","image":"image/b111fd55-7a75-4f3b-a51f-b6ced7b29933.png","allDocument":"Mục Lục [Thu / Mở] Lịch sử Kiến trúc Hồ Văn Văn Miếu Môn Đại Trung Môn Khuê Văn Các Giếng Thiên Quang, bia Tiến sĩ Đại Thành Môn, khu điện thờ Đền Khải Thánh - Quốc Tử Giám Nhà Tiền đường, Hậu đường Những tu bổ sau năm 1954 Đánh giá Ý nghĩa Xem thêm Ghi chú Tham khảo Tài liệu Sơ đồ kiến trúc quần thể Văn Miếu - Quốc Tử Giám ngày nay Bản đồ Văn Miếu - Quốc Tử Giám (chữ Hán:文廟 - 國子監) là quần thể di tích đa dạng và phong phú hàng đầu của thành phố Hà Nội, nằm ở phía Nam kinh thành Thăng Long. Hiện nay, nơi đây đã được thủ tướng chính phủ Việt Nam đưa vào danh sách xếp hạng 23 di tích quốc gia đặc biệt. Quần thể kiến trúc Văn Miếu - Quốc Tử Giám bao gồm: hồ Văn, khu Văn Miếu - Quốc Tử Giám và vườn Giám và kiến trúc chủ thể là Văn Miếu - nơi thờ Khổng Tử và Quốc Tử Giám - trường đại học đầu tiên của Việt Nam. Khu Văn Miếu - Quốc Tử Giám có tường gạch vồ bao quanh, phía trong chia thành 5 lớp không gian với các kiến trúc khác nhau. Mỗi lớp không gian đó được giới hạn bởi các tường gạch có 3 cửa để thông với nhau (gồm cửa chính giữa và hai cửa phụ hai bên). Từ ngoài vào trong có các cổng lần lượt là: cổng Văn Miếu, Đại Trung, Đại Thành và cổng Thái Học. Với hơn 700 năm hoạt động đã đào tạo hàng nghìn nhân tài cho đất nước. Ngày nay, Văn Miếu Quốc Tử Giám là nơi tham quan của du khách trong và ngoài nước đồng thời cũng là nơi khen tặng cho học sinh xuất sắc và còn là nơi tổ chức hội thơ hàng năm vào ngày rằm tháng giêng. Đây từng là nơi các sĩ tử đến \"cầu may\" trước mỗi kỳ thi bằng cách vuốt đầu rùa tại các bia tiến sĩ, tuy nhiên, ngày nay, để bảo tồn di tích, một hàng rào được thiết lập và các sĩ tử không còn làm nghi thức cầu may như trước nữa.Nơi này là nơi trên tờ tiền polymer 100.000 VND của Việt Nam Lịch sử","source":"https://nguoikesu.com/dia-danh/van-mieu-quoc-tu-giam"}]